pynnacle_genesis/__init__.py
pynnacle_genesis/main.py
pynnacle_genesis-1.1.1.dist-info/licenses/LICENSE.txt
pynnacle_genesis-1.1.1.dist-info/METADATA
pynnacle_genesis-1.1.1.dist-info/WHEEL
pynnacle_genesis-1.1.1.dist-info/top_level.txt
pynnacle_genesis-1.1.1.dist-info/RECORD
