Metadata-Version: 2.4
Name: pynnacle_genesis
Version: 1.1.1
Summary: A Python module for the Pinnacle Genesis board, offering hands-on robotics coding with a familiar structure inspired by popular development board environments.
Home-page: https://github.com/Red-Pula/pynnacle-genesis
Author: Rafael Red Angelo M. Hizon, Jenel M. Justo, Serena Mae C.S. Lee
Author-email: redhizon@gmail.com, jenel.just88@gmail.com, nmae.lee@gmail.com
License: GNU Affero General Public License
Classifier: Intended Audience :: Education
Classifier: Topic :: Education
Classifier: Topic :: Software Development :: Embedded Systems
Classifier: License :: OSI Approved :: GNU Affero General Public License v3
Classifier: Operating System :: OS Independent
Classifier: Programming Language :: Python :: 3.7
Classifier: Programming Language :: Python :: 3.8
Classifier: Programming Language :: Python :: 3.9
Classifier: Programming Language :: Python :: 3.10
Classifier: Programming Language :: Python :: 3.11
Classifier: Programming Language :: Python :: 3.12
Classifier: Programming Language :: Python :: 3.13
License-File: LICENSE.txt
Requires-Dist: pymata4>=1.15
Requires-Dist: pyserial>=3.5
Dynamic: author
Dynamic: author-email
Dynamic: classifier
Dynamic: description
Dynamic: description-content-type
Dynamic: home-page
Dynamic: license
Dynamic: license-file
Dynamic: requires-dist
Dynamic: summary
